[
  {
    "api": "/api/emotions",
    "method": "GET",
    "responseTime": 24.40679999999702,
    "timestamp": "2025-06-04T13:52:15.825Z",
    "statusCode": 200,
    "success": true
  },
  {
    "api": "/api/emotions",
    "method": "GET",
    "responseTime": 8.36610000001383,
    "timestamp": "2025-06-04T13:52:15.833Z",
    "statusCode": 200,
    "success": true
  },
  {
    "api": "/api/emotions",
    "method": "GET",
    "responseTime": 6.816599999991013,
    "timestamp": "2025-06-04T13:52:15.840Z",
    "statusCode": 200,
    "success": true
  }
]