[
  {
    "api": "/api/emotions",
    "method": "GET",
    "responseTime": 23.962400000018533,
    "timestamp": "2025-06-08T13:42:11.239Z",
    "statusCode": 200,
    "success": true
  },
  {
    "api": "/api/emotions",
    "method": "GET",
    "responseTime": 8.951299999986077,
    "timestamp": "2025-06-08T13:42:11.248Z",
    "statusCode": 200,
    "success": true
  },
  {
    "api": "/api/emotions",
    "method": "GET",
    "responseTime": 6.731599999999162,
    "timestamp": "2025-06-08T13:42:11.255Z",
    "statusCode": 200,
    "success": true
  }
]