[
  {
    "api": "/api/emotions",
    "method": "GET",
    "responseTime": 27.56800000000021,
    "timestamp": "2025-03-20T06:50:15.634Z",
    "statusCode": 200,
    "success": true
  },
  {
    "api": "/api/emotions",
    "method": "GET",
    "responseTime": 7.480199999999968,
    "timestamp": "2025-03-20T06:50:15.641Z",
    "statusCode": 200,
    "success": true
  },
  {
    "api": "/api/emotions",
    "method": "GET",
    "responseTime": 8.270599999999831,
    "timestamp": "2025-03-20T06:50:15.650Z",
    "statusCode": 200,
    "success": true
  },
  {
    "api": "/api/emotions",
    "method": "GET",
    "responseTime": 6.4494000000004235,
    "timestamp": "2025-03-20T06:50:15.656Z",
    "statusCode": 200,
    "success": true
  },
  {
    "api": "/api/emotions",
    "method": "GET",
    "responseTime": 6.536200000000463,
    "timestamp": "2025-03-20T06:50:15.663Z",
    "statusCode": 200,
    "success": true
  },
  {
    "api": "/api/emotions",
    "method": "GET",
    "responseTime": 7.815000000000509,
    "timestamp": "2025-03-20T06:50:15.671Z",
    "statusCode": 200,
    "success": true
  },
  {
    "api": "/api/emotions",
    "method": "GET",
    "responseTime": 6.456400000000031,
    "timestamp": "2025-03-20T06:50:15.677Z",
    "statusCode": 200,
    "success": true
  },
  {
    "api": "/api/emotions",
    "method": "GET",
    "responseTime": 6.579399999999623,
    "timestamp": "2025-03-20T06:50:15.684Z",
    "statusCode": 200,
    "success": true
  },
  {
    "api": "/api/emotions",
    "method": "GET",
    "responseTime": 6.929199999999582,
    "timestamp": "2025-03-20T06:50:15.691Z",
    "statusCode": 200,
    "success": true
  },
  {
    "api": "/api/emotions",
    "method": "GET",
    "responseTime": 7.914300000000367,
    "timestamp": "2025-03-20T06:50:15.699Z",
    "statusCode": 200,
    "success": true
  },
  {
    "api": "/api/users/profile",
    "method": "GET",
    "responseTime": 11.433399999999892,
    "timestamp": "2025-03-20T06:50:15.712Z",
    "statusCode": 200,
    "success": true
  },
  {
    "api": "/api/users/profile",
    "method": "GET",
    "responseTime": 7.52849999999944,
    "timestamp": "2025-03-20T06:50:15.719Z",
    "statusCode": 200,
    "success": true
  },
  {
    "api": "/api/users/profile",
    "method": "GET",
    "responseTime": 8.337399999999434,
    "timestamp": "2025-03-20T06:50:15.728Z",
    "statusCode": 200,
    "success": true
  },
  {
    "api": "/api/users/profile",
    "method": "GET",
    "responseTime": 7.66360000000077,
    "timestamp": "2025-03-20T06:50:15.735Z",
    "statusCode": 200,
    "success": true
  },
  {
    "api": "/api/users/profile",
    "method": "GET",
    "responseTime": 7.230099999999766,
    "timestamp": "2025-03-20T06:50:15.743Z",
    "statusCode": 200,
    "success": true
  },
  {
    "api": "/api/users/profile",
    "method": "GET",
    "responseTime": 8.511199999999917,
    "timestamp": "2025-03-20T06:50:15.751Z",
    "statusCode": 200,
    "success": true
  },
  {
    "api": "/api/users/profile",
    "method": "GET",
    "responseTime": 7.365499999999884,
    "timestamp": "2025-03-20T06:50:15.758Z",
    "statusCode": 200,
    "success": true
  },
  {
    "api": "/api/users/profile",
    "method": "GET",
    "responseTime": 7.755400000000009,
    "timestamp": "2025-03-20T06:50:15.766Z",
    "statusCode": 200,
    "success": true
  },
  {
    "api": "/api/users/profile",
    "method": "GET",
    "responseTime": 8.283199999999852,
    "timestamp": "2025-03-20T06:50:15.774Z",
    "statusCode": 200,
    "success": true
  },
  {
    "api": "/api/users/profile",
    "method": "GET",
    "responseTime": 7.168899999999667,
    "timestamp": "2025-03-20T06:50:15.782Z",
    "statusCode": 200,
    "success": true
  },
  {
    "api": "/api/my-day/posts",
    "method": "GET",
    "responseTime": 27.111899999999878,
    "timestamp": "2025-03-20T06:50:15.810Z",
    "statusCode": 200,
    "success": true
  },
  {
    "api": "/api/my-day/posts",
    "method": "GET",
    "responseTime": 17.33100000000013,
    "timestamp": "2025-03-20T06:50:15.827Z",
    "statusCode": 200,
    "success": true
  },
  {
    "api": "/api/my-day/posts",
    "method": "GET",
    "responseTime": 17.66689999999926,
    "timestamp": "2025-03-20T06:50:15.845Z",
    "statusCode": 200,
    "success": true
  },
  {
    "api": "/api/my-day/posts",
    "method": "GET",
    "responseTime": 18.58559999999943,
    "timestamp": "2025-03-20T06:50:15.864Z",
    "statusCode": 200,
    "success": true
  },
  {
    "api": "/api/my-day/posts",
    "method": "GET",
    "responseTime": 16.576599999999416,
    "timestamp": "2025-03-20T06:50:15.880Z",
    "statusCode": 200,
    "success": true
  },
  {
    "api": "/api/my-day/posts",
    "method": "GET",
    "responseTime": 15.897400000000744,
    "timestamp": "2025-03-20T06:50:15.896Z",
    "statusCode": 200,
    "success": true
  },
  {
    "api": "/api/my-day/posts",
    "method": "GET",
    "responseTime": 17.144900000000234,
    "timestamp": "2025-03-20T06:50:15.913Z",
    "statusCode": 200,
    "success": true
  },
  {
    "api": "/api/my-day/posts",
    "method": "GET",
    "responseTime": 17.30919999999969,
    "timestamp": "2025-03-20T06:50:15.931Z",
    "statusCode": 200,
    "success": true
  },
  {
    "api": "/api/my-day/posts",
    "method": "GET",
    "responseTime": 16.175599999999577,
    "timestamp": "2025-03-20T06:50:15.947Z",
    "statusCode": 200,
    "success": true
  },
  {
    "api": "/api/my-day/posts",
    "method": "GET",
    "responseTime": 16.462099999999737,
    "timestamp": "2025-03-20T06:50:15.963Z",
    "statusCode": 200,
    "success": true
  },
  {
    "api": "/api/notifications",
    "method": "GET",
    "responseTime": 10.247699999999895,
    "timestamp": "2025-03-20T06:50:15.975Z",
    "statusCode": 200,
    "success": true
  },
  {
    "api": "/api/notifications",
    "method": "GET",
    "responseTime": 9.005099999999402,
    "timestamp": "2025-03-20T06:50:15.984Z",
    "statusCode": 200,
    "success": true
  },
  {
    "api": "/api/notifications",
    "method": "GET",
    "responseTime": 8.76759999999922,
    "timestamp": "2025-03-20T06:50:15.993Z",
    "statusCode": 200,
    "success": true
  },
  {
    "api": "/api/notifications",
    "method": "GET",
    "responseTime": 8.348199999999451,
    "timestamp": "2025-03-20T06:50:16.001Z",
    "statusCode": 200,
    "success": true
  },
  {
    "api": "/api/notifications",
    "method": "GET",
    "responseTime": 7.951200000000426,
    "timestamp": "2025-03-20T06:50:16.009Z",
    "statusCode": 200,
    "success": true
  },
  {
    "api": "/api/notifications",
    "method": "GET",
    "responseTime": 9.29359999999997,
    "timestamp": "2025-03-20T06:50:16.018Z",
    "statusCode": 200,
    "success": true
  },
  {
    "api": "/api/notifications",
    "method": "GET",
    "responseTime": 7.9935999999997875,
    "timestamp": "2025-03-20T06:50:16.026Z",
    "statusCode": 200,
    "success": true
  },
  {
    "api": "/api/notifications",
    "method": "GET",
    "responseTime": 7.772699999999531,
    "timestamp": "2025-03-20T06:50:16.034Z",
    "statusCode": 200,
    "success": true
  },
  {
    "api": "/api/notifications",
    "method": "GET",
    "responseTime": 8.356899999999769,
    "timestamp": "2025-03-20T06:50:16.042Z",
    "statusCode": 200,
    "success": true
  },
  {
    "api": "/api/notifications",
    "method": "GET",
    "responseTime": 7.895099999999729,
    "timestamp": "2025-03-20T06:50:16.050Z",
    "statusCode": 200,
    "success": true
  },
  {
    "api": "/api/my-day/posts",
    "method": "POST",
    "responseTime": 29.938199999999597,
    "timestamp": "2025-03-20T06:50:16.082Z",
    "statusCode": 201,
    "success": true
  },
  {
    "api": "/api/my-day/posts",
    "method": "POST",
    "responseTime": 11.699599999999919,
    "timestamp": "2025-03-20T06:50:16.093Z",
    "statusCode": 201,
    "success": true
  },
  {
    "api": "/api/my-day/posts",
    "method": "POST",
    "responseTime": 12.671700000000783,
    "timestamp": "2025-03-20T06:50:16.106Z",
    "statusCode": 201,
    "success": true
  },
  {
    "api": "/api/my-day/posts",
    "method": "POST",
    "responseTime": 12.482899999999972,
    "timestamp": "2025-03-20T06:50:16.119Z",
    "statusCode": 201,
    "success": true
  },
  {
    "api": "/api/my-day/posts",
    "method": "POST",
    "responseTime": 24.323999999999614,
    "timestamp": "2025-03-20T06:50:16.143Z",
    "statusCode": 201,
    "success": true
  },
  {
    "api": "/api/my-day/posts",
    "method": "POST",
    "responseTime": 19.50669999999991,
    "timestamp": "2025-03-20T06:50:16.162Z",
    "statusCode": 201,
    "success": true
  },
  {
    "api": "/api/my-day/posts",
    "method": "POST",
    "responseTime": 10.92489999999998,
    "timestamp": "2025-03-20T06:50:16.173Z",
    "statusCode": 201,
    "success": true
  },
  {
    "api": "/api/my-day/posts",
    "method": "POST",
    "responseTime": 10.72269999999935,
    "timestamp": "2025-03-20T06:50:16.184Z",
    "statusCode": 201,
    "success": true
  },
  {
    "api": "/api/my-day/posts",
    "method": "POST",
    "responseTime": 10.979600000000573,
    "timestamp": "2025-03-20T06:50:16.195Z",
    "statusCode": 201,
    "success": true
  },
  {
    "api": "/api/my-day/posts",
    "method": "POST",
    "responseTime": 10.713700000000244,
    "timestamp": "2025-03-20T06:50:16.206Z",
    "statusCode": 201,
    "success": true
  },
  {
    "api": "/api/someone-day",
    "method": "GET",
    "responseTime": 19.24420000000009,
    "timestamp": "2025-03-20T06:50:16.226Z",
    "statusCode": 200,
    "success": true
  },
  {
    "api": "/api/someone-day",
    "method": "GET",
    "responseTime": 15.719900000000052,
    "timestamp": "2025-03-20T06:50:16.242Z",
    "statusCode": 200,
    "success": true
  },
  {
    "api": "/api/someone-day",
    "method": "GET",
    "responseTime": 15.531599999999344,
    "timestamp": "2025-03-20T06:50:16.258Z",
    "statusCode": 200,
    "success": true
  },
  {
    "api": "/api/someone-day",
    "method": "GET",
    "responseTime": 16.427699999999277,
    "timestamp": "2025-03-20T06:50:16.274Z",
    "statusCode": 200,
    "success": true
  },
  {
    "api": "/api/someone-day",
    "method": "GET",
    "responseTime": 15.498400000000402,
    "timestamp": "2025-03-20T06:50:16.290Z",
    "statusCode": 200,
    "success": true
  },
  {
    "api": "/api/someone-day",
    "method": "GET",
    "responseTime": 15.10439999999926,
    "timestamp": "2025-03-20T06:50:16.305Z",
    "statusCode": 200,
    "success": true
  },
  {
    "api": "/api/someone-day",
    "method": "GET",
    "responseTime": 15.799800000000687,
    "timestamp": "2025-03-20T06:50:16.321Z",
    "statusCode": 200,
    "success": true
  },
  {
    "api": "/api/someone-day",
    "method": "GET",
    "responseTime": 15.679000000000087,
    "timestamp": "2025-03-20T06:50:16.336Z",
    "statusCode": 200,
    "success": true
  },
  {
    "api": "/api/someone-day",
    "method": "GET",
    "responseTime": 15.488599999999678,
    "timestamp": "2025-03-20T06:50:16.352Z",
    "statusCode": 200,
    "success": true
  },
  {
    "api": "/api/someone-day",
    "method": "GET",
    "responseTime": 15.785300000000461,
    "timestamp": "2025-03-20T06:50:16.368Z",
    "statusCode": 200,
    "success": true
  },
  {
    "api": "/api/tags",
    "method": "GET",
    "responseTime": 7.061399999999594,
    "timestamp": "2025-03-20T06:50:16.376Z",
    "statusCode": 200,
    "success": true
  },
  {
    "api": "/api/tags",
    "method": "GET",
    "responseTime": 6.23949999999968,
    "timestamp": "2025-03-20T06:50:16.382Z",
    "statusCode": 200,
    "success": true
  },
  {
    "api": "/api/tags",
    "method": "GET",
    "responseTime": 6.825300000000425,
    "timestamp": "2025-03-20T06:50:16.389Z",
    "statusCode": 200,
    "success": true
  },
  {
    "api": "/api/tags",
    "method": "GET",
    "responseTime": 6.324300000000221,
    "timestamp": "2025-03-20T06:50:16.395Z",
    "statusCode": 200,
    "success": true
  },
  {
    "api": "/api/tags",
    "method": "GET",
    "responseTime": 6.203700000000026,
    "timestamp": "2025-03-20T06:50:16.402Z",
    "statusCode": 200,
    "success": true
  },
  {
    "api": "/api/tags",
    "method": "GET",
    "responseTime": 6.554500000000189,
    "timestamp": "2025-03-20T06:50:16.408Z",
    "statusCode": 200,
    "success": true
  },
  {
    "api": "/api/tags",
    "method": "GET",
    "responseTime": 5.999299999999494,
    "timestamp": "2025-03-20T06:50:16.414Z",
    "statusCode": 200,
    "success": true
  },
  {
    "api": "/api/tags",
    "method": "GET",
    "responseTime": 5.983100000000377,
    "timestamp": "2025-03-20T06:50:16.420Z",
    "statusCode": 200,
    "success": true
  },
  {
    "api": "/api/tags",
    "method": "GET",
    "responseTime": 5.964699999999539,
    "timestamp": "2025-03-20T06:50:16.426Z",
    "statusCode": 200,
    "success": true
  },
  {
    "api": "/api/tags",
    "method": "GET",
    "responseTime": 7.00919999999951,
    "timestamp": "2025-03-20T06:50:16.433Z",
    "statusCode": 200,
    "success": true
  }
]