[
  {
    "api": "/api/emotions",
    "method": "GET",
    "responseTime": 25.80360000001383,
    "timestamp": "2025-06-06T14:54:17.125Z",
    "statusCode": 200,
    "success": true
  },
  {
    "api": "/api/emotions",
    "method": "GET",
    "responseTime": 10.518400000000838,
    "timestamp": "2025-06-06T14:54:17.136Z",
    "statusCode": 200,
    "success": true
  },
  {
    "api": "/api/emotions",
    "method": "GET",
    "responseTime": 8.301100000011502,
    "timestamp": "2025-06-06T14:54:17.144Z",
    "statusCode": 200,
    "success": true
  }
]